browsergym/workarena/__init__.py
browsergym/workarena/config.py
browsergym/workarena/install.py
browsergym/workarena/instance.py
browsergym/workarena/utils.py
browsergym/workarena/api/__init__.py
browsergym/workarena/api/category.py
browsergym/workarena/api/change_request.py
browsergym/workarena/api/computer_asset.py
browsergym/workarena/api/cost_center.py
browsergym/workarena/api/expense_line.py
browsergym/workarena/api/incident.py
browsergym/workarena/api/knowledge.py
browsergym/workarena/api/problem.py
browsergym/workarena/api/report.py
browsergym/workarena/api/requested_items.py
browsergym/workarena/api/requests.py
browsergym/workarena/api/system_properties.py
browsergym/workarena/api/ui_themes.py
browsergym/workarena/api/user.py
browsergym/workarena/api/utils.py
browsergym/workarena/data_files/setup_files/forms/expected_change_request_form_fields.json
browsergym/workarena/data_files/setup_files/forms/expected_hardware_form_fields.json
browsergym/workarena/data_files/setup_files/forms/expected_incident_form_fields.json
browsergym/workarena/data_files/setup_files/forms/expected_problem_form_fields.json
browsergym/workarena/data_files/setup_files/forms/expected_request_item_form_fields.json
browsergym/workarena/data_files/setup_files/forms/expected_user_form_fields.json
browsergym/workarena/data_files/setup_files/knowledge/kb_autopublish_workflow.xml
browsergym/workarena/data_files/setup_files/knowledge/knowledge_base.json
browsergym/workarena/data_files/setup_files/knowledge/protocols.json
browsergym/workarena/data_files/setup_files/knowledge/test.html
browsergym/workarena/data_files/setup_files/lists/expected_asset_list_columns.json
browsergym/workarena/data_files/setup_files/lists/expected_change_request_list_columns.json
browsergym/workarena/data_files/setup_files/lists/expected_expense_line_list_columns.json
browsergym/workarena/data_files/setup_files/lists/expected_hardware_list_columns.json
browsergym_workarena-0.5.1.dist-info/METADATA
browsergym_workarena-0.5.1.dist-info/WHEEL
browsergym_workarena-0.5.1.dist-info/entry_points.txt
browsergym_workarena-0.5.1.dist-info/licenses/LICENSE
browsergym_workarena-0.5.1.dist-info/RECORD
