Metadata-Version: 2.4
Name: browsergym-workarena
Version: 0.5.1
Summary: WorkArena benchmark for BrowserGym
Project-URL: homepage, https://github.com/ServiceNow/WorkArena
Author: Léo Boisvert, Alex Drouin, Maxime Gasse, Alex Lacoste, Manuel Del Verme, Megh Thakkar
License: Apache-2.0
License-File: LICENSE
Classifier: Development Status :: 2 - Pre-Alpha
Classifier: Intended Audience :: Science/Research
Classifier: License :: OSI Approved :: Apache Software License
Classifier: Operating System :: OS Independent
Classifier: Programming Language :: Python :: 3
Classifier: Topic :: Scientific/Engineering :: Artificial Intelligence
Requires-Python: >3.7
Requires-Dist: browsergym-core>=0.2
Requires-Dist: english-words>=2.0.1
Requires-Dist: faker>=24.8.0
Requires-Dist: huggingface-hub>=0.23
Requires-Dist: numpy>=1.14
Requires-Dist: requests>=2.31
Requires-Dist: tenacity>=8.2.3
Requires-Dist: tqdm>=4.66.2
